MANIFEST.in
README.txt
setup.py
Sphinx_Explorer.egg-info/PKG-INFO
Sphinx_Explorer.egg-info/SOURCES.txt
Sphinx_Explorer.egg-info/dependency_links.txt
Sphinx_Explorer.egg-info/entry_points.txt
Sphinx_Explorer.egg-info/requires.txt
Sphinx_Explorer.egg-info/top_level.txt
sphinx_explorer/__init__.py
sphinx_explorer/about.py
sphinx_explorer/bookmark.py
sphinx_explorer/dialogs.py
sphinx_explorer/i18n.py
sphinx_explorer/main_window.py
sphinx_explorer/package_mgr.py
sphinx_explorer/plugin_dialog.py
sphinx_explorer/project_list_model.py
sphinx_explorer/system_settings.py
sphinx_explorer/theme_dialog.py
sphinx_explorer/generator/__init__.py
sphinx_explorer/generator/quickstart.py
sphinx_explorer/plugin/__init__.py
sphinx_explorer/plugin/editor.py
sphinx_explorer/plugin/extension.py
sphinx_explorer/plugin/template_model.py
sphinx_explorer/project_tools/__init__.py
sphinx_explorer/project_tools/project_tree.py
sphinx_explorer/property_widget/__init__.py
sphinx_explorer/property_widget/default_value_dict.py
sphinx_explorer/property_widget/define.py
sphinx_explorer/property_widget/description_widget.py
sphinx_explorer/property_widget/property_model.py
sphinx_explorer/property_widget/property_widget.py
sphinx_explorer/property_widget/frames/__init__.py
sphinx_explorer/property_widget/frames/tree_dialog_frame.py
sphinx_explorer/property_widget/pages/__init__.py
sphinx_explorer/property_widget/value_types/__init__.py
sphinx_explorer/property_widget/value_types/type_base.py
sphinx_explorer/property_widget/value_types/type_list.py
sphinx_explorer/property_widget/widgets/__init__.py
sphinx_explorer/python_venv/__init__.py
sphinx_explorer/python_venv/package_model.py
sphinx_explorer/python_venv/tasks.py
sphinx_explorer/sphinx_value_types/__init__.py
sphinx_explorer/sphinx_value_types/pages.py
sphinx_explorer/sphinx_value_types/sphinx_value_types.py
sphinx_explorer/sphinx_value_types/widgets.py
sphinx_explorer/task/__init__.py
sphinx_explorer/ui/__init__.py
sphinx_explorer/ui/main_window_ui.py
sphinx_explorer/ui/quickstart_dialog_ui.py
sphinx_explorer/ui/quickstart_widget_ui.py
sphinx_explorer/ui/settings_ui.py
sphinx_explorer/ui/theme_dialog_ui.py
sphinx_explorer/util/QConsoleWidget.py
sphinx_explorer/util/__init__.py
