Metadata-Version: 1.0
Name: Sphinx-Explorer
Version: 0.99
Summary: Python documentation generator
Home-page: https://github.com/pashango2/sphinx-explorer
Author: Toshiyuki Ishii.
Author-email: pashango2@gmail.com
License: MIT
Platform: any
